Metadata-Version: 1.0
Name: gauscalc
Version: 1.0
Summary: Calculate and Plot Gaussian and Binomail distributions
Home-page: UNKNOWN
Author: Abdullah Alam Tapadar
Author-email: abdullah.alam.tapadar2000@gmail.com
License: UNKNOWN
Platform: UNKNOWN
